Workbook

Sheet 资产负债表
A1: 项目 | B1: 金额 | E1: 项目 | F1: 金额 | I1: 项目 | J1: 金额
A2: 报表日期 | B2: 45291 | E2: 报表日期 | F2: 45657 | I2: 报表日期 | J2: 46022
A3: 流动资产 | B3: 流动资产 | E3: 流动资产 | F3: 流动资产 | I3: 流动资产 | J3: 流动资产
A4: 货币资金 | B4: 155825.2 | E4: 货币资金 | F4: 205585.68 | I4: 货币资金 | J4: 239685.15
A5: 交易性金融资产 | B5: 72380.03 | E5: 交易性金融资产 | F5: 69397.27 | I5: 交易性金融资产 | J5: 109406.76
A6: 衍生金融资产 | B6: 0 | E6: 衍生金融资产 | F6: 0 | I6: 衍生金融资产 | J6: 0
A7: 应收票据及应收账款 | B7: 92611.04 | E7: 应收票据及应收账款 | F7: 90050.85 | I7: 应收票据及应收账款 | J7: 92724.39
A8: 应收票据 | B8: 9964.27 | E8: 应收票据 | F8: 5134 | I8: 应收票据 | J8: 3750.07
A9: 应收账款 | B9: 82646.77 | E9: 应收账款 | F9: 84916.85 | I9: 应收账款 | J9: 88974.32
A10: 应收款项融资 | B10: 1824.82 | E10: 应收款项融资 | F10: 1018.49 | I10: 应收款项融资 | J10: 1033.53
A11: 预付款项 | B11: 5186.34 | E11: 预付款项 | F11: 9434.03 | I11: 预付款项 | J11: 7023.31
A12: 其他应收款(合计) | B12: 2216.88 | E12: 其他应收款(合计) | F12: 2310.75 | I12: 其他应收款(合计) | J12: 3545.22
A13: 应收利息 | B13: 0 | E13: 应收利息 | F13: 0 | I13: 应收利息 | J13: 0
A14: 应收股利 | B14: 0 | E14: 应收股利 | F14: 0 | I14: 应收股利 | J14: 126.72
A15: 其他应收款 | B15: 2216.88 | E15: 其他应收款 | F15: 2310.75 | I15: 其他应收款 | J15: 0
... A23: 流动资产合计 | B23: 556969.49 | E23: 流动资产合计 | F23: 601106.63 | I23: 流动资产合计 | J23: 665924.86
A24: 非流动资产 | B24: 非流动资产 | E24: 非流动资产 | F24: 非流动资产 | I24: 非流动资产 | J24: 非流动资产
A25: 发放贷款及垫款 | B25: 0 | E25: 发放贷款及垫款 | F25: 0 | I25: 发放贷款及垫款 | J25: 0
A26: 可供出售金融资产 | B26: 0 | E26: 可供出售金融资产 | F26: 0 | I26: 可供出售金融资产 | J26: 0
A27: 持有至到期投资 | B27: 0 | E27: 持有至到期投资 | F27: 0 | I27: 持有至到期投资 | J27: 0
A28: 长期应收款 | B28: 0 | E28: 长期应收款 | F28: 0 | I28: 长期应收款 | J28: 0
A29: 长期股权投资 | B29: 14353.75 | E29: 长期股权投资 | F29: 12008.43 | I29: 长期股权投资 | J29: 9987.79
A30: 投资性房地产 | B30: 1957.82 | E30: 投资性房地产 | F30: 1867.55 | I30: 投资性房地产 | J30: 1777.29
A31: 在建工程(合计) | B31: 86849.69 | E31: 在建工程(合计) | F31: 9502.67 | I31: 在建工程(合计) | J31: 9015.72
A32: 在建工程 | B32: 38311.33 | E32: 在建工程 | F32: 7704.77 | I32: 在建工程 | J32: 0
A33: 工程物资 | B33: 48538.35 | E33: 工程物资 | F33: 1797.91 | I33: 工程物资 | J33: 0
A34: 固定资产及清理(合计) | B34: 559769.25 | E34: 固定资产及清理(合计) | F34: 605375.6 | I34: 固定资产及清理(合计) | J34: 570532.57
A35: 固定资产净额 | B35: 559769.25 | E35: 固定资产净额 | F35: 605375.6 | I35: 固定资产净额 | J35: 570532.57
A36: 固定资产清理 | B36: 0 | E36: 固定资产清理 | F36: 0 | I36: 固定资产清理 | J36: 0
... A48: 资产总计 | B48: 1343028.6 | E48: 资产总计 | F48: 1392971.6 | I48: 资产总计 | J48: 1410676.3
A49: 流动负债 | B49: 流动负债 | E49: 流动负债 | F49: 流动负债 | I49: 流动负债 | J49: 流动负债
A50: 短期借款 | B50: 58070.48 | E50: 短期借款 | F50: 84968.68 | I50: 短期借款 | J50: 65283.69
A51: 交易性金融负债 | B51: 4678.58 | E51: 交易性金融负债 | F51: 1585.87 | I51: 交易性金融负债 | J51: 0
A52: 应付票据及应付账款 | B52: 27550.29 | E52: 应付票据及应付账款 | F52: 27207.91 | I52: 应付票据及应付账款 | J52: 23234.82
A53: 应付票据 | B53: 0 | E53: 应付票据 | F53: 0 | I53: 应付票据 | J53: 0
A54: 应付账款 | B54: 27550.29 | E54: 应付账款 | F54: 27207.91 | I54: 应付账款 | J54: 23234.82
A55: 预收款项 | B55: 0 | E55: 预收款项 | F55: 0 | I55: 预收款项 | J55: 0
A56: 应付手续费及佣金 | B56: 0 | E56: 应付手续费及佣金 | F56: 0 | I56: 应付手续费及佣金 | J56: 0
A57: 应付职工薪酬 | B57: 28434.5 | E57: 应付职工薪酬 | F57: 30122.74 | I57: 应付职工薪酬 | J57: 30149.72
A58: 应交税费 | B58: 4263.32 | E58: 应交税费 | F58: 5726.19 | I58: 应交税费 | J58: 5887.34
A59: 其他应付款(合计) | B59: 4754.94 | E59: 其他应付款(合计) | F59: 1743.78 | I59: 其他应付款(合计) | J59: 1758.08
A60: 应付利息 | B60: 0 | E60: 应付利息 | F60: 0 | I60: 应付利息 | J60: 0
A61: 应付股利 | B61: 44.11 | E61: 应付股利 | F61: 44.11 | I61: 应付股利 | J61: 44.11
... A68: 流动负债合计 | B68: 162544.85 | E68: 流动负债合计 | F68: 177572.08 | I68: 流动负债合计 | J68: 334636.64
A69: 非流动负债 | B69: 非流动负债 | E69: 非流动负债 | F69: 非流动负债 | I69: 非流动负债 | J69: 非流动负债
A70: 长期借款 | B70: 25999.3 | E70: 长期借款 | F70: 39624.41 | I70: 长期借款 | J70: 24791.27
A71: 应付债券 | B71: 147657.21 | E71: 应付债券 | F71: 150942.04 | I71: 应付债券 | J71: 0
A72: 租赁负债 | B72: 8658.02 | E72: 租赁负债 | F72: 9135.33 | I72: 租赁负债 | J72: 7415.93
A73: 长期应付职工薪酬 | B73: 5727.67 | E73: 长期应付职工薪酬 | F73: 5849.5 | I73: 长期应付职工薪酬 | J73: 5824.13
A74: 长期应付款(合计) | B74: 0 | E74: 长期应付款(合计) | F74: 0 | I74: 长期应付款(合计) | J74: 0
A75: 长期应付款 | B75: 0 | E75: 长期应付款 | F75: 0 | I75: 长期应付款 | J75: 0
A76: 专项应付款 | B76: 0 | E76: 专项应付款 | F76: 0 | I76: 专项应付款 | J76: 0
A77: 预计非流动负债 | B77: 0 | E77: 预计非流动负债 | F77: 0 | I77: 预计非流动负债 | J77: 0
A78: 递延所得税负债 | B78: 15517.88 | E78: 递延所得税负债 | F78: 13151.9 | I78: 递延所得税负债 | J78: 11051.43
A79: 长期递延收益 | B79: 15176.89 | E79: 长期递延收益 | F79: 14539.51 | I79: 长期递延收益 | J79: 13947.33
A80: 其他非流动负债 | B80: 0 | E80: 其他非流动负债 | F80: 0 | I80: 其他非流动负债 | J80: 0
A81: 非流动负债合计 | B81: 218736.97 | E81: 非流动负债合计 | F81: 233242.7 | I81: 非流动负债合计 | J81: 63030.09
A82: 负债合计 | B82: 381281.82 | E82: 负债合计 | F82: 410814.78 | I82: 负债合计 | J82: 397666.73
A83: 所有者权益 | B83: 所有者权益 | E83: 所有者权益 | F83: 所有者权益 | I83: 所有者权益 | J83: 所有者权益
A84: 实收资本(或股本) | B84: 86360.76 | E84: 实收资本(或股本) | F84: 81730.6 | I84: 实收资本(或股本) | J84: 81730.69
A85: 资本公积 | B85: 33479.26 | E85: 资本公积 | F85: 17851.87 | I85: 资本公积 | J85: 17893.22
A86: 减：库存股 | B86: 19343.87 | E86: 减：库存股 | F86: 0 | I86: 减：库存股 | J86: 0
A87: 其他综合收益 | B87: 13134.31 | E87: 其他综合收益 | F87: 16692.6 | I87: 其他综合收益 | J87: 10871.3
A88: 专项储备 | B88: 0 | E88: 专项储备 | F88: 0 | I88: 专项储备 | J88: 0
A89: 盈余公积 | B89: 126066.1 | E89: 盈余公积 | F89: 127142.93 | I89: 盈余公积 | J89: 133121.86
A90: 一般风险准备 | B90: 0 | E90: 一般风险准备 | F90: 0 | I90: 一般风险准备 | J90: 0
A91: 未分配利润 | B91: 676245.75 | E91: 未分配利润 | F91: 693316.5 | I91: 未分配利润 | J91: 730350.05
A92: 归属于母公司股东权益合计 | B92: 923080.69 | E92: 归属于母公司股东权益合计 | F92: 943872.84 | I92: 归属于母公司股东权益合计 | J92: 981105.42
A93: 少数股东权益 | B93: 38666.11 | E93: 少数股东权益 | F93: 38283.95 | I93: 少数股东权益 | J93: 31904.14
A94: 所有者权益(或股东权益)合计 | B94: 961746.8 | E94: 所有者权益(或股东权益)合计 | F94: 982156.78 | I94: 所有者权益(或股东权益)合计 | J94: 1013009.6
A95: 负债和所有者权益(或股东权益)总计 | B95: 1343028.6 | E95: 负债和所有者权益(或股东权益)总计 | F95: 1392971.6 | I95: 负债和所有者权益(或股东权益)总计 | J95: 1410676.3

Sheet 利润表
A1: 项目 | B1: 金额 | E1: 项目 | F1: 金额 | I1: 项目 | J1: 金额
A2: 报表日期 | B2: 45291 | E2: 报表日期 | F2: 45657 | I2: 报表日期 | J2: 46022
A3: 一、营业总收入 | B3: 596147.73 | E3: 一、营业总收入 | F3: 609061.5 | I3: 一、营业总收入 | J3: 590430.87
A4: 营业收入 | B4: 596147.73 | E4: 营业收入 | F4: 609061.5 | I4: 营业收入 | J4: 590430.87
A5: 二、营业总成本 | B5: 543065.54 | E5: 二、营业总成本 | F5: 540443.15 | I5: 二、营业总成本 | J5: 534297.19
A6: 营业成本 | B6: 459138.89 | E6: 营业成本 | F6: 464357.89 | I6: 营业成本 | J6: 454612.42
A7: 营业税金及附加 | B7: 6326 | E7: 营业税金及附加 | F7: 6245.04 | I7: 营业税金及附加 | J7: 6169.31
A8: 销售费用 | B8: 14845.48 | E8: 销售费用 | F8: 15100.44 | I8: 销售费用 | J8: 14794.95
A9: 管理费用 | B9: 38232.75 | E9: 管理费用 | F9: 34432.7 | I9: 管理费用 | J9: 33749.87
A10: 财务费用 | B10: 544.88 | E10: 财务费用 | F10: -375.02 | I10: 财务费用 | J10: 5747.35
A11: 研发费用 | B11: 23977.53 | E11: 研发费用 | F11: 20682.09 | I11: 研发费用 | J11: 19223.28
A12: 资产减值损失 | B12: 0 | E12: 资产减值损失 | F12: 0 | I12: 资产减值损失 | J12: 0
A13: 公允价值变动收益 | B13: -6502.07 | E13: 公允价值变动收益 | F13: -9082.68 | I13: 公允价值变动收益 | J13: -5580.52
... A25: 少数股东损益 | B25: -709.18 | E25: 少数股东损益 | F25: 1594.03 | I25: 少数股东损益 | J25: 1120.62
A26: 六、每股收益 | B26: nan | E26: 六、每股收益 | F26: nan | I26: 六、每股收益 | J26: nan
A27: 基本每股收益(元/股) | B27: 0.47 | E27: 基本每股收益(元/股) | F27: 0.5 | I27: 基本每股收益(元/股) | J27: 0.73
A28: 稀释每股收益(元/股) | B28: 0.42 | E28: 稀释每股收益(元/股) | F28: 0.47 | I28: 稀释每股收益(元/股) | J28: 0.66
A29: 七、其他综合收益 | B29: 2371.78 | E29: 七、其他综合收益 | F29: 3558.98 | I29: 七、其他综合收益 | J29: -5821.72
A30: 八、综合收益总额 | B30: 42007.02 | E30: 八、综合收益总额 | F30: 46185.15 | I30: 八、综合收益总额 | J30: 54657.5
A31: 归属于母公司所有者的综合收益总额 | B31: 42715.85 | E31: 归属于母公司所有者的综合收益总额 | F31: 44590.42 | I31: 归属于母公司所有者的综合收益总额 | J31: 53537.31
A32: 归属于少数股东的综合收益总额 | B32: -708.83 | E32: 归属于少数股东的综合收益总额 | F32: 1594.73 | I32: 归属于少数股东的综合收益总额 | J32: 1120.2

Sheet 现金流量表
A1: 项目 | B1: 金额 | E1: 项目 | F1: 金额 | I1: 项目 | J1: 金额
A2: 报表日期 | B2: 45291 | E2: 报表日期 | F2: 45657 | I2: 报表日期 | J2: 46022
A3: 一、经营活动产生的现金流量 | B3: 一、经营活动产生的现金流量 | E3: 一、经营活动产生的现金流量 | F3: 一、经营活动产生的现金流量 | I3: 一、经营活动产生的现金流量 | J3: 一、经营活动产生的现金流量
A4: 销售商品、提供劳务收到的现金 | B4: 549242.43 | E4: 销售商品、提供劳务收到的现金 | F4: 600466.64 | I4: 销售商品、提供劳务收到的现金 | J4: 569701.8
A5: 收到的税费返还 | B5: 12549.67 | E5: 收到的税费返还 | F5: 7107.93 | I5: 收到的税费返还 | J5: 6269.28
A6: 收到的其他与经营活动有关的现金 | B6: 11536.65 | E6: 收到的其他与经营活动有关的现金 | F6: 4453.66 | I6: 收到的其他与经营活动有关的现金 | J6: 5558.24
A7: 经营活动现金流入小计 | B7: 573328.75 | E7: 经营活动现金流入小计 | F7: 612028.23 | I7: 经营活动现金流入小计 | J7: 581529.32
A8: 购买商品、接受劳务支付的现金 | B8: 300827.48 | E8: 购买商品、接受劳务支付的现金 | F8: 304082.59 | I8: 购买商品、接受劳务支付的现金 | J8: 314725.97
A9: 支付给职工以及为职工支付的现金 | B9: 156565.39 | E9: 支付给职工以及为职工支付的现金 | F9: 155161.85 | I9: 支付给职工以及为职工支付的现金 | J9: 156270.16
A10: 支付的各项税费 | B10: 14623.08 | E10: 支付的各项税费 | F10: 13155.15 | I10: 支付的各项税费 | J10: 20646.68
A11: 支付的其他与经营活动有关的现金 | B11: 15826.35 | E11: 支付的其他与经营活动有关的现金 | F11: 15207.44 | I11: 支付的其他与经营活动有关的现金 | J11: 18636.77
A12: 经营活动现金流出小计 | B12: 487842.3 | E12: 经营活动现金流出小计 | F12: 487607.02 | I12: 经营活动现金流出小计 | J12: 510279.58
A13: 经营活动产生的现金流量净额 | B13: 85486.45 | E13: 经营活动产生的现金流量净额 | F13: 124421.22 | I13: 经营活动产生的现金流量净额 | J13: 71249.74
A14: 二、投资活动产生的现金流量 | B14: 二、投资活动产生的现金流量 | E14: 二、投资活动产生的现金流量 | F14: 二、投资活动产生的现金流量 | I14: 二、投资活动产生的现金流量 | J14: 二、投资活动产生的现金流量
A15: 收回投资所收到的现金 | B15: 946514.19 | E15: 收回投资所收到的现金 | F15: 102026.1 | I15: 收回投资所收到的现金 | J15: 1044580.1
A16: 取得投资收益所收到的现金 | B16: 5780.57 | E16: 取得投资收益所收到的现金 | F16: 726.1 | I16: 取得投资收益所收到的现金 | J16: 26055.44
A17: 处置固定资产、无形资产和其他长期资产所收回的现金净额 | B17: 639.14 | E17: 处置固定资产、无形资产和其他长期资产所收回的现金净额 | F17: 111.84 | I17: 处置固定资产、无形资产和其他长期资产所收回的现金净额 | J17: 933.46
A18: 处置子公司及其他营业单位收到的现金净额 | B18: 0 | E18: 处置子公司及其他营业单位收到的现金净额 | F18: 0 | I18: 处置子公司及其他营业单位收到的现金净额 | J18: 0
A19: 收到的其他与投资活动有关的现金 | B19: 15333.28 | E19: 收到的其他与投资活动有关的现金 | F19: 71964.89 | I19: 收到的其他与投资活动有关的现金 | J19: 89541.88
A20: 投资活动现金流入小计 | B20: 968267.18 | E20: 投资活动现金流入小计 | F20: 174828.93 | I20: 投资活动现金流入小计 | J20: 1161110.8
A21: 购建固定资产、无形资产和其他长期资产所支付的现金 | B21: 84676.88 | E21: 购建固定资产、无形资产和其他长期资产所支付的现金 | F21: 21746.16 | I21: 购建固定资产、无形资产和其他长期资产所支付的现金 | J21: 18905.31
A22: 投资所支付的现金 | B22: 966406.87 | E22: 投资所支付的现金 | F22: 122522.72 | I22: 投资所支付的现金 | J22: 1075551.7
A23: 取得子公司及其他营业单位支付的现金净额 | B23: 0 | E23: 取得子公司及其他营业单位支付的现金净额 | F23: 0 | I23: 取得子公司及其他营业单位支付的现金净额 | J23: 0
A24: 支付的其他与投资活动有关的现金 | B24: 12507.39 | E24: 支付的其他与投资活动有关的现金 | F24: 153771.7 | I24: 支付的其他与投资活动有关的现金 | J24: 37986.52
A25: 投资活动现金流出小计 | B25: 1063591.1 | E25: 投资活动现金流出小计 | F25: 298040.58 | I25: 投资活动现金流出小计 | J25: 1132443.5
A26: 投资活动产生的现金流量净额 | B26: -95323.95 | E26: 投资活动产生的现金流量净额 | F26: -123211.65 | I26: 投资活动产生的现金流量净额 | J26: 28667.29
A27: 三、筹资活动产生的现金流量 | B27: 三、筹资活动产生的现金流量 | E27: 三、筹资活动产生的现金流量 | F27: 三、筹资活动产生的现金流量 | I27: 三、筹资活动产生的现金流量 | J27: 三、筹资活动产生的现金流量
A28: 吸收投资收到的现金 | B28: 0 | E28: 吸收投资收到的现金 | F28: 0 | I28: 吸收投资收到的现金 | J28: 0
A29: 其中：子公司吸收少数股东投资收到的现金 | B29: 0 | E29: 其中：子公司吸收少数股东投资收到的现金 | F29: 0 | I29: 其中：子公司吸收少数股东投资收到的现金 | J29: 0
A30: 取得借款收到的现金 | B30: 128962.52 | E30: 取得借款收到的现金 | F30: 214698.66 | I30: 取得借款收到的现金 | J30: 160245.26
A31: 发行债券收到的现金 | B31: 0 | E31: 发行债券收到的现金 | F31: 0 | I31: 发行债券收到的现金 | J31: 0
A32: 收到其他与筹资活动有关的现金 | B32: 9.88 | E32: 收到其他与筹资活动有关的现金 | F32: 0 | I32: 收到其他与筹资活动有关的现金 | J32: 0
A33: 筹资活动现金流入小计 | B33: 128972.4 | E33: 筹资活动现金流入小计 | F33: 214698.66 | I33: 筹资活动现金流入小计 | J33: 160245.26
A34: 偿还债务支付的现金 | B34: 134590.22 | E34: 偿还债务支付的现金 | F34: 182288.56 | I34: 偿还债务支付的现金 | J34: 162750.75
A35: 分配股利、利润或偿付利息所支付的现金 | B35: 14033.74 | E35: 分配股利、利润或偿付利息所支付的现金 | F35: 29329.76 | I35: 分配股利、利润或偿付利息所支付的现金 | J35: 30055.87
A36: 其中：子公司支付给少数股东的股利、利润 | B36: 0 | E36: 其中：子公司支付给少数股东的股利、利润 | F36: 0 | I36: 其中：子公司支付给少数股东的股利、利润 | J36: 7500
A37: 支付其他与筹资活动有关的现金 | B37: 19114.43 | E37: 支付其他与筹资活动有关的现金 | F37: 5879.01 | I37: 支付其他与筹资活动有关的现金 | J37: 1874.45
A38: 筹资活动现金流出小计 | B38: 167738.4 | E38: 筹资活动现金流出小计 | F38: 217497.33 | I38: 筹资活动现金流出小计 | J38: 194681.08
A39: 筹资活动产生的现金流量净额 | B39: -38766 | E39: 筹资活动产生的现金流量净额 | F39: -2798.66 | I39: 筹资活动产生的现金流量净额 | J39: -34435.82
... A43: 六、期末现金及现金等价物余额 | B43: 135361.53 | E43: 六、期末现金及现金等价物余额 | F43: 137141.23 | I43: 六、期末现金及现金等价物余额 | J43: 203343.95
A44: 附注 | B44: 附注 | E44: 附注 | F44: 附注 | I44: 附注 | J44: 附注
A45: 净利润 | B45: 39635.24 | E45: 净利润 | F45: 42626.17 | I45: 净利润 | J45: 60479.22
A46: 少数股东权益 | B46: 0 | E46: 少数股东权益 | F46: 0 | I46: 少数股东权益 | J46: 0
A47: 未确认的投资损失 | B47: 0 | E47: 未确认的投资损失 | F47: 0 | I47: 未确认的投资损失 | J47: 0
A48: 资产减值准备 | B48: 10817.68 | E48: 资产减值准备 | F48: 11314.12 | I48: 资产减值准备 | J48: 11549.95
A49: 固定资产折旧、油气资产折耗、生产性物资折旧 | B49: 46454.78 | E49: 固定资产折旧、油气资产折耗、生产性物资折旧 | F49: 47870.32 | I49: 固定资产折旧、油气资产折耗、生产性物资折旧 | J49: 48143.61
A50: 无形资产摊销 | B50: 1057.74 | E50: 无形资产摊销 | F50: 1075.74 | I50: 无形资产摊销 | J50: 1093.25
A51: 长期待摊费用摊销 | B51: 399.1 | E51: 长期待摊费用摊销 | F51: 199.25 | I51: 长期待摊费用摊销 | J51: 277.8
A52: 待摊费用的减少 | B52: 0 | E52: 待摊费用的减少 | F52: 0 | I52: 待摊费用的减少 | J52: 0
A53: 预提费用的增加 | B53: 0 | E53: 预提费用的增加 | F53: 0 | I53: 预提费用的增加 | J53: 0
A54: 处置固定资产、无形资产和其他长期资产的损失 | B54: 912.33 | E54: 处置固定资产、无形资产和其他长期资产的损失 | F54: 313.95 | I54: 处置固定资产、无形资产和其他长期资产的损失 | J54: -55.75
A55: 固定资产报废损失 | B55: 61.84 | E55: 固定资产报废损失 | F55: 234.23 | I55: 固定资产报废损失 | J55: 9.72
A56: 公允价值变动损失 | B56: 6502.07 | E56: 公允价值变动损失 | F56: 9082.68 | I56: 公允价值变动损失 | J56: 5580.52
... A77: 现金及现金等价物的净增加额 | B77: -46928.2 | E77: 现金及现金等价物的净增加额 | F77: 1779.7 | I77: 现金及现金等价物的净增加额 | J77: 66202.72

Sheet 盈利能力分析
A1: 盈利能力分析 | B1: 2024年 | C1: 2025年 | D1: 增长率
A2: 营业利润率 | B2: =利润表!F17/利润表!F4 -> 0.076637597 | C2: =利润表!J17/利润表!J4 -> 0.11505576 | D2: =(C2-B2)/B2 -> 0.50129649
A3: 销售利润率 | B3: =利润表!F23/利润表!F4 -> 0.069986643 | C3: =利润表!J23/利润表!J4 -> 0.10243235 | D3: =(C3-B3)/B3 -> 0.46359852
A4: 成本费用利润率 | B4: =利润表!F23/SUM(利润表!F6:利润表!F11) -> 0.078872627 | C4: =利润表!J23/SUM(利润表!J6:利润表!J11) -> 0.11319397 | D4: =(C4-B4)/B4 -> 0.43514901
A5: 净资产收益率 | B5: =利润表!F23/((资产负债表!B94+资产负债表!F94)/2) -> 0.04385626 | C5: =利润表!J23/((资产负债表!F94+资产负债表!J94)/2) -> 0.060625742 | D5: =(C5-B5)/B5 -> 0.38237375
A6: 总资产报酬率 | B6: =(利润表!F21+利润表!F10)/((资产负债表!B48+资产负债表!F48)/2) -> 0.033922564 | C6: =(利润表!J21+利润表!J10)/((资产负债表!F48+资产负债表!J48)/2) -> 0.053545512 | D6: =(C6-B6)/B6 -> 0.57846302

Sheet 偿债能力分析
A1: 偿债能力分析 | B1: 2024年 | C1: 2025年 | D1: 增长率
A2: 现金比率 | B2: =资产负债表!F4/资产负债表!F68 -> 1.157759 | C2: =资产负债表!J4/资产负债表!J68 -> 0.71625495 | D2: =(C2-B2)/B2 -> -0.38134367
A3: 速动比率 | B3: =(资产负债表!F23-资产负债表!F17)/资产负债表!F68 -> 2.2476405 | C3: =(资产负债表!J23-资产负债表!J17)/资产负债表!J68 -> 1.360266 | D3: =(C3-B3)/B3 -> -0.39480265
A4: 流动比率 | B4: =资产负债表!F23/资产负债表!F68 -> 3.3851416 | C4: =资产负债表!J23/资产负债表!J68 -> 1.9899939 | D4: =(C4-B4)/B4 -> -0.41213866
A5: 产权比率 | B5: =资产负债表!F82/资产负债表!F94 -> 0.41827821 | C5: =资产负债表!J82/资产负债表!J94 -> 0.3925597 | D5: =(C5-B5)/B5 -> -0.06148661
